experimentum/__init__.py
experimentum/__version__.py
experimentum/cli.py
experimentum/files.py
experimentum/quickstart.py
experimentum/utils.py
experimentum/Commands/AbstractCommand.py
experimentum/Commands/CommandManager.py
experimentum/Commands/ExperimentsCommand.py
experimentum/Commands/MigrationCommand.py
experimentum/Commands/PlotCommand.py
experimentum/Commands/WebGUICommand.py
experimentum/Commands/__init__.py
experimentum/Config/Config.py
experimentum/Config/Loader.py
experimentum/Config/__init__.py
experimentum/Experiments/App.py
experimentum/Experiments/DataBag.py
experimentum/Experiments/Experiment.py
experimentum/Experiments/Performance.py
experimentum/Experiments/__init__.py
experimentum/Plots/Factory.py
experimentum/Plots/Plot.py
experimentum/Plots/__init__.py
experimentum/Storage/AbstractRepository.py
experimentum/Storage/AbstractStore.py
experimentum/Storage/__init__.py
experimentum/Storage/Migrations/Blueprint.py
experimentum/Storage/Migrations/Column.py
experimentum/Storage/Migrations/ForeignKey.py
experimentum/Storage/Migrations/Migration.py
experimentum/Storage/Migrations/Migrator.py
experimentum/Storage/Migrations/Schema.py
experimentum/Storage/Migrations/__init__.py
experimentum/Storage/Migrations/migration.stub
experimentum/Storage/SQLAlchemy/ColumnFactory.py
experimentum/Storage/SQLAlchemy/Platform.py
experimentum/Storage/SQLAlchemy/Repository.py
experimentum/Storage/SQLAlchemy/SQLitePlatform.py
experimentum/Storage/SQLAlchemy/Store.py
experimentum/Storage/SQLAlchemy/__init__.py
experimentum/WebGUI/__init__.py
experimentum/WebGUI/helpers.py
experimentum/WebGUI/static/app.js
experimentum/WebGUI/static/event-stream.js
experimentum/WebGUI/static/migrations.js
experimentum/WebGUI/static/plots.js
experimentum/WebGUI/static/styles.css
experimentum/WebGUI/static/utils.js
experimentum/WebGUI/templates/404.jinja
experimentum/WebGUI/templates/layout.jinja
experimentum/WebGUI/templates/dashboard/index.jinja
experimentum-1.0.3.dist-info/LICENSE.md
experimentum-1.0.3.dist-info/METADATA
experimentum-1.0.3.dist-info/WHEEL
experimentum-1.0.3.dist-info/entry_points.txt
experimentum-1.0.3.dist-info/top_level.txt
experimentum-1.0.3.dist-info/RECORD
