Metadata-Version: 2.1
Name: experimentum
Version: 1.0.3
Summary: Data-Management Framework for Running and Analyzing Computational Experiments
Home-page: https://github.com/PascalKleindienst/experimentum
Author: Pascal Kleindienst
Author-email: mail@pascalkleindienst.de
License: Apache
Platform: UNKNOWN
Classifier: Development Status :: 5 - Production/Stable
Classifier: Environment :: Console
Classifier: Environment :: Web Environment
Classifier: Intended Audience :: Developers
Classifier: Intended Audience :: Information Technology
Classifier: Intended Audience :: Science/Research
Classifier: License :: OSI Approved :: Apache Software License
Classifier: Programming Language :: Python
Classifier: Programming Language :: Python :: 2
Classifier: Programming Language :: Python :: 2.7
Classifier: Programming Language :: Python :: 3
Classifier: Programming Language :: Python :: 3.4
Classifier: Programming Language :: Python :: 3.5
Classifier: Programming Language :: Python :: 3.6
Classifier: Programming Language :: Python :: 3.7
Classifier: Programming Language :: Python :: Implementation :: CPython
Classifier: Topic :: Database
Classifier: Topic :: Scientific/Engineering
Classifier: Topic :: Utilities
Requires-Python: >=2.7.0
Requires-Dist: SQLAlchemy (>=1.2.0)
Requires-Dist: termcolor
Requires-Dist: colorama
Requires-Dist: tabulate
Requires-Dist: inflection
Requires-Dist: six
Requires-Dist: psutil
Requires-Dist: matplotlib
Requires-Dist: Flask (>=1.0.0)
Provides-Extra: mssql
Requires-Dist: pyodbc ; extra == 'mssql'
Provides-Extra: mssql_pymssql
Requires-Dist: pymssql ; extra == 'mssql_pymssql'
Provides-Extra: mssql_pyodbc
Requires-Dist: pyodbc ; extra == 'mssql_pyodbc'
Provides-Extra: mysql
Requires-Dist: mysqlclient ; extra == 'mysql'
Provides-Extra: oracle
Requires-Dist: cx-oracle ; extra == 'oracle'
Provides-Extra: postgresql
Requires-Dist: psycopg2 ; extra == 'postgresql'
Provides-Extra: postgresql_pg8000
Requires-Dist: pg8000 ; extra == 'postgresql_pg8000'
Provides-Extra: postgresql_psycopg2binary
Requires-Dist: psycopg2-binary ; extra == 'postgresql_psycopg2binary'
Provides-Extra: postgresql_psycopg2cffi
Requires-Dist: psycopg2cffi ; extra == 'postgresql_psycopg2cffi'
Provides-Extra: pymysql
Requires-Dist: pymysql ; extra == 'pymysql'
